Workbook

Sheet 00_Cover
B2: Northline Consumer Products
B3: Unlevered DCF Valuation Model
B5: What this file is
B6: A five-year unlevered DCF for a fictional CPG company. It builds free cash flow from operating assumptions, discounts at WACC, adds a Gordon-growth terminal value, and bridges to equity value, NPV, and IRR.
B8: How to use
B9: 1. Edit yellow cells (blue font) on 01_Assumptions.
B10: 2. Read the FCF build on 02_FCF_Build (all formulas).
B11: 3. Check WACC on 03_WACC.
B12: 4. Read enterprise value, equity value, NPV, and IRR on 04_Valuation.
B13: 5. Stress WACC vs terminal growth on 05_Sensitivity.
B15: File conventions
B16: Yellow cells with blue font = inputs. Black font = formulas.
... B21: https://github.com/saisiri-bandaru

Sheet 01_Assumptions
B2: Assumptions
B3: Yellow + blue = inputs. Change these; everything else recalculates.
B5: Forecast years | C5: Year 0 (LTM) | D5: Year 1 | E5: Year 2 | F5: Year 3 | G5: Year 4 | H5: Year 5
B7: Revenue ($000s) | C7: 850000
B8: Revenue growth | C8: — | D8: 0.08 | E8: 0.07 | F8: 0.06 | G8: 0.05 | H8: 0.04
B9: Revenue (built) | C9: =C7 | D9: =C9*(1+D8) | E9: =D9*(1+E8) | F9: =E9*(1+F8) | G9: =F9*(1+G8) | H9: =G9*(1+H8)
B11: EBITDA margin | C11: 0.14 | D11: 0.145 | E11: 0.15 | F11: 0.155 | G11: 0.16 | H11: 0.16
B12: D&A % of revenue | C12: 0.035 | D12: 0.035 | E12: 0.034 | F12: 0.034 | G12: 0.033 | H12: 0.033
B13: Capex % of revenue | C13: 0.04 | D13: 0.04 | E13: 0.038 | F13: 0.037 | G13: 0.036 | H13: 0.035
B14: NWC % of revenue | C14: 0.12 | D14: 0.118 | E14: 0.116 | F14: 0.114 | G14: 0.112 | H14: 0.11
B16: Tax rate | C16: 0.25
B18: WACC inputs
B19: Risk-free rate | C19: 0.04
B20: Equity risk premium | C20: 0.05
B21: Beta (levered) | C21: 1.05
B22: Pre-tax cost of debt | C22: 0.055
B23: Target debt weight D/(D+E) | C23: 0.25
B25: Terminal value
B26: Terminal growth (g) | C26: 0.025
B27: Note: g must stay below WACC.
B29: Equity bridge
B30: Net debt / (net cash) ($000s) | C30: 120000
B31: Shares outstanding (000s) | C31: 40000
B33: Discounting
B34: Mid-year convention (1=yes, 0=year-end) | C34: 1
B36: Units: $000s throughout unless noted.

Sheet 02_FCF_Build
B2: Unlevered free cash flow build
B3: All rows are formulas from 01_Assumptions.
C5: Year 0 (LTM) | D5: Year 1 | E5: Year 2 | F5: Year 3 | G5: Year 4 | H5: Year 5
B6: Revenue | C6: ='01_Assumptions'!C9 | D6: ='01_Assumptions'!D9 | E6: ='01_Assumptions'!E9 | F6: ='01_Assumptions'!F9 | G6: ='01_Assumptions'!G9 | H6: ='01_Assumptions'!H9
B7: EBITDA margin | C7: ='01_Assumptions'!C11 | D7: ='01_Assumptions'!D11 | E7: ='01_Assumptions'!E11 | F7: ='01_Assumptions'!F11 | G7: ='01_Assumptions'!G11 | H7: ='01_Assumptions'!H11
B8: EBITDA | C8: =C6*C7 | D8: =D6*D7 | E8: =E6*E7 | F8: =F6*F7 | G8: =G6*G7 | H8: =H6*H7
B9: D&A | C9: =C6*'01_Assumptions'!C12 | D9: =D6*'01_Assumptions'!D12 | E9: =E6*'01_Assumptions'!E12 | F9: =F6*'01_Assumptions'!F12 | G9: =G6*'01_Assumptions'!G12 | H9: =H6*'01_Assumptions'!H12
B10: EBIT | C10: =C8-C9 | D10: =D8-D9 | E10: =E8-E9 | F10: =F8-F9 | G10: =G8-G9 | H10: =H8-H9
B11: Tax on EBIT | C11: =C10*'01_Assumptions'!$C$16 | D11: =D10*'01_Assumptions'!$C$16 | E11: =E10*'01_Assumptions'!$C$16 | F11: =F10*'01_Assumptions'!$C$16 | G11: =G10*'01_Assumptions'!$C$16 | H11: =H10*'01_Assumptions'!$C$16
B12: NOPAT | C12: =C10-C11 | D12: =D10-D11 | E12: =E10-E11 | F12: =F10-F11 | G12: =G10-G11 | H12: =H10-H11
B13: + D&A | C13: =C9 | D13: =D9 | E13: =E9 | F13: =F9 | G13: =G9 | H13: =H9
B14: Gross cash flow | C14: =C12+C13 | D14: =D12+D13 | E14: =E12+E13 | F14: =F12+F13 | G14: =G12+G13 | H14: =H12+H13
B15: Capex | C15: =C6*'01_Assumptions'!C13 | D15: =D6*'01_Assumptions'!D13 | E15: =E6*'01_Assumptions'!E13 | F15: =F6*'01_Assumptions'!F13 | G15: =G6*'01_Assumptions'!G13 | H15: =H6*'01_Assumptions'!H13
B16: NWC balance | C16: =C6*'01_Assumptions'!C14 | D16: =D6*'01_Assumptions'!D14 | E16: =E6*'01_Assumptions'!E14 | F16: =F6*'01_Assumptions'!F14 | G16: =G6*'01_Assumptions'!G14 | H16: =H6*'01_Assumptions'!H14
B17: Δ NWC (use of cash) | C17: =0 | D17: =D16-C16 | E17: =E16-D16 | F17: =F16-E16 | G17: =G16-F16 | H17: =H16-G16
B18: Unlevered FCF | C18: =C14-C15-C17 | D18: =D14-D15-D17 | E18: =E14-E15-E17 | F18: =F14-F15-F17 | G18: =G14-G15-G17 | H18: =H14-H15-H17
B20: Note: Year 0 FCF is shown for reference; valuation discounts Year 1–5 FCFs only.

Sheet 03_WACC
B2: WACC
B3: Capital structure weights × after-tax costs.
B5: Cost of equity (CAPM)
B6: Risk-free rate | C6: ='01_Assumptions'!C19
B7: Equity risk premium | C7: ='01_Assumptions'!C20
B8: Beta | C8: ='01_Assumptions'!C21
B9: Cost of equity | C9: =C6+C8*C7
B11: Cost of debt
B12: Pre-tax cost of debt | C12: ='01_Assumptions'!C22
B13: Tax rate | C13: ='01_Assumptions'!C16
B14: After-tax cost of debt | C14: =C12*(1-C13)
B16: Weights
B17: Debt weight | C17: ='01_Assumptions'!C23
B18: Equity weight | C18: =1-C17
B20: WACC
B21: WACC | C21: =C18*C9+C17*C14 | D21: =C18*C9 + C17*C14

Sheet 04_Valuation
B2: Valuation summary
B3: Discount forecast FCFs at WACC; terminal value via Gordon growth on Year-5 FCF.
B5: Enterprise value | C5: =C28
B6: Less: net debt | C6: ='01_Assumptions'!C30
B7: Equity value | C7: =C5-C6
B8: Equity value / share ($) | C8: =C7/'01_Assumptions'!C31
B10: NPV of FCFs + TV (at t0) | C10: =C28
B11: Implied IRR (Y1–Y5 FCF + TV vs EV) | C11: =C32
B13: Discount factors & PV of FCF
C14: Year 1 | D14: Year 2 | E14: Year 3 | F14: Year 4 | G14: Year 5
B15: Unlevered FCF | C15: ='02_FCF_Build'!D18 | D15: ='02_FCF_Build'!E18 | E15: ='02_FCF_Build'!F18 | F15: ='02_FCF_Build'!G18 | G15: ='02_FCF_Build'!H18
B16: WACC | C16: ='03_WACC'!$C$21 | D16: =C16 | E16: =C16 | F16: =C16 | G16: =C16
B17: Time (years) | C17: =IF('01_Assumptions'!$C$34=1,0.5,1) | D17: =C17+1 | E17: =D17+1 | F17: =E17+1 | G17: =F17+1
B18: Discount factor | C18: =1/(1+C16)^C17 | D18: =1/(1+$C$16)^D17 | E18: =1/(1+$C$16)^E17 | F18: =1/(1+$C$16)^F17 | G18: =1/(1+$C$16)^G17
B19: PV of FCF | C19: =C15*C18 | D19: =D15*D18 | E19: =E15*E18 | F19: =F15*F18 | G19: =G15*G18
B21: Terminal value (Gordon growth)
B22: g | C22: ='01_Assumptions'!C26
B23: Year-5 FCF | C23: =G15
B24: TV at Year 5 = FCF5*(1+g)/(WACC-g) | C24: =C23*(1+C22)/(C16-C22)
B25: PV of TV | C25: =C24*G18
B27: PV of explicit FCFs (Y1–Y5) | C27: =SUM(C19:G19)
B28: Enterprise value (= PV FCF + PV TV) | C28: =C27+C25
B30: IRR check
B31: Cash flows for IRR: -EV at t0, then FCF1..FCF4, FCF5+TV
B32: IRR | C32: =IRR(C33:H33)
B33: IRR cash flows | C33: =-C28 | D33: =C15 | E33: =D15 | F33: =E15 | G33: =F15 | H33: =G15+C24
C34: t0 | D34: Y1 | E34: Y2 | F34: Y3 | G34: Y4 | H34: Y5+TV
B36: IRR should approximately equal WACC when TV and FCFs are consistent with the discount rate (small differences from mid-year timing).

Sheet 05_Sensitivity
B2: Sensitivity — Equity value ($000s)
B3: Rows: WACC. Columns: terminal growth g. Each cell re-discounts FCFs with that WACC/g.
B5: Base equity value | C5: ='04_Valuation'!C7
B7: WACC \ g | C7: 0.015 | D7: 0.02 | E7: 0.025 | F7: 0.03 | G7: 0.035
B8: 0.075 | C8: =('04_Valuation'!$C$15/(1+$B8)^0.5+'04_Valuation'!$D$15/(1+$B8)^1.5+'04_Valuation'!$E$15/(1+$B8)^2.5+'04_Valuation'!$F$15/(1+$B8)^3.5+'04_Valuation'!$G$15/(1+$B8)^4.5+('04_Valuation'!$G$15*(1+0.015)/($B8-0.015))/(1+$B8)^4.5)-'01_Assumptions'!$C$30 | D8: =('04_Valuation'!$C$15/(1+$B8)^0.5+'04_Valuation'!$D$15/(1+$B8)^1.5+'04_Valuation'!$E$15/(1+$B8)^2.5+'04_Valuation'!$F$15/(1+$B8)^3.5+'04_Valuation'!$G$15/(1+$B8)^4.5+('04_Valuation'!$G$15*(1+0.02)/($B8-0.02))/(1+$B8)^4.5)-'01_Assumptions'!$C$30 | E8: =('04_Valuation'!$C$15/(1+$B8)^0.5+'04_Valuation'!$D$15/(1+$B8)^1.5+'04_Valuation'!$E$15/(1+$B8)^2.5+'04_Valuation'!$F$15/(1+$B8)^3.5+'04_Valuation'!$G$15/(1+$B8)^4.5+('04_Valuation'!$G$15*(1+0.025)/($B8-0.025))/(1+$B8)^4.5)-'01_Assumptions'!$C$30 | F8: =('04_Valuation'!$C$15/(1+$B8)^0.5+'04_Valuation'!$D$15/(1+$B8)^1.5+'04_Valuation'!$E$15/(1+$B8)^2.5+'04_Valuation'!$F$15/(1+$B8)^3.5+'04_Valuation'!$G$15/(1+$B8)^4.5+('04_Valuation'!$G$15*(1+0.03)/($B8-0.03))/(1+$B8)^4.5)-'01_Assumptions'!$C$30 | G8: =('04_Valuation'!$C$15/(1+$B8)^0.5+'04_Valuation'!$D$15/(1+$B8)^1.5+'04_Valuation'!$E$15/(1+$B8)^2.5+'04_Valuation'!$F$15/(1+$B8)^3.5+'04_Valuation'!$G$15/(1+$B8)^4.5+('04_Valuation'!$G$15*(1+0.035)/($B8-0.035))/(1+$B8)^4.5)-'01_Assumptions'!$C$30
B9: 0.085 | C9: =('04_Valuation'!$C$15/(1+$B9)^0.5+'04_Valuation'!$D$15/(1+$B9)^1.5+'04_Valuation'!$E$15/(1+$B9)^2.5+'04_Valuation'!$F$15/(1+$B9)^3.5+'04_Valuation'!$G$15/(1+$B9)^4.5+('04_Valuation'!$G$15*(1+0.015)/($B9-0.015))/(1+$B9)^4.5)-'01_Assumptions'!$C$30 | D9: =('04_Valuation'!$C$15/(1+$B9)^0.5+'04_Valuation'!$D$15/(1+$B9)^1.5+'04_Valuation'!$E$15/(1+$B9)^2.5+'04_Valuation'!$F$15/(1+$B9)^3.5+'04_Valuation'!$G$15/(1+$B9)^4.5+('04_Valuation'!$G$15*(1+0.02)/($B9-0.02))/(1+$B9)^4.5)-'01_Assumptions'!$C$30 | E9: =('04_Valuation'!$C$15/(1+$B9)^0.5+'04_Valuation'!$D$15/(1+$B9)^1.5+'04_Valuation'!$E$15/(1+$B9)^2.5+'04_Valuation'!$F$15/(1+$B9)^3.5+'04_Valuation'!$G$15/(1+$B9)^4.5+('04_Valuation'!$G$15*(1+0.025)/($B9-0.025))/(1+$B9)^4.5)-'01_Assumptions'!$C$30 | F9: =('04_Valuation'!$C$15/(1+$B9)^0.5+'04_Valuation'!$D$15/(1+$B9)^1.5+'04_Valuation'!$E$15/(1+$B9)^2.5+'04_Valuation'!$F$15/(1+$B9)^3.5+'04_Valuation'!$G$15/(1+$B9)^4.5+('04_Valuation'!$G$15*(1+0.03)/($B9-0.03))/(1+$B9)^4.5)-'01_Assumptions'!$C$30 | G9: =('04_Valuation'!$C$15/(1+$B9)^0.5+'04_Valuation'!$D$15/(1+$B9)^1.5+'04_Valuation'!$E$15/(1+$B9)^2.5+'04_Valuation'!$F$15/(1+$B9)^3.5+'04_Valuation'!$G$15/(1+$B9)^4.5+('04_Valuation'!$G$15*(1+0.035)/($B9-0.035))/(1+$B9)^4.5)-'01_Assumptions'!$C$30
B10: 0.095 | C10: =('04_Valuation'!$C$15/(1+$B10)^0.5+'04_Valuation'!$D$15/(1+$B10)^1.5+'04_Valuation'!$E$15/(1+$B10)^2.5+'04_Valuation'!$F$15/(1+$B10)^3.5+'04_Valuation'!$G$15/(1+$B10)^4.5+('04_Valuation'!$G$15*(1+0.015)/($B10-0.015))/(1+$B10)^4.5)-'01_Assumptions'!$C$30 | D10: =('04_Valuation'!$C$15/(1+$B10)^0.5+'04_Valuation'!$D$15/(1+$B10)^1.5+'04_Valuation'!$E$15/(1+$B10)^2.5+'04_Valuation'!$F$15/(1+$B10)^3.5+'04_Valuation'!$G$15/(1+$B10)^4.5+('04_Valuation'!$G$15*(1+0.02)/($B10-0.02))/(1+$B10)^4.5)-'01_Assumptions'!$C$30 | E10: =('04_Valuation'!$C$15/(1+$B10)^0.5+'04_Valuation'!$D$15/(1+$B10)^1.5+'04_Valuation'!$E$15/(1+$B10)^2.5+'04_Valuation'!$F$15/(1+$B10)^3.5+'04_Valuation'!$G$15/(1+$B10)^4.5+('04_Valuation'!$G$15*(1+0.025)/($B10-0.025))/(1+$B10)^4.5)-'01_Assumptions'!$C$30 | F10: =('04_Valuation'!$C$15/(1+$B10)^0.5+'04_Valuation'!$D$15/(1+$B10)^1.5+'04_Valuation'!$E$15/(1+$B10)^2.5+'04_Valuation'!$F$15/(1+$B10)^3.5+'04_Valuation'!$G$15/(1+$B10)^4.5+('04_Valuation'!$G$15*(1+0.03)/($B10-0.03))/(1+$B10)^4.5)-'01_Assumptions'!$C$30 | G10: =('04_Valuation'!$C$15/(1+$B10)^0.5+'04_Valuation'!$D$15/(1+$B10)^1.5+'04_Valuation'!$E$15/(1+$B10)^2.5+'04_Valuation'!$F$15/(1+$B10)^3.5+'04_Valuation'!$G$15/(1+$B10)^4.5+('04_Valuation'!$G$15*(1+0.035)/($B10-0.035))/(1+$B10)^4.5)-'01_Assumptions'!$C$30
B11: 0.105 | C11: =('04_Valuation'!$C$15/(1+$B11)^0.5+'04_Valuation'!$D$15/(1+$B11)^1.5+'04_Valuation'!$E$15/(1+$B11)^2.5+'04_Valuation'!$F$15/(1+$B11)^3.5+'04_Valuation'!$G$15/(1+$B11)^4.5+('04_Valuation'!$G$15*(1+0.015)/($B11-0.015))/(1+$B11)^4.5)-'01_Assumptions'!$C$30 | D11: =('04_Valuation'!$C$15/(1+$B11)^0.5+'04_Valuation'!$D$15/(1+$B11)^1.5+'04_Valuation'!$E$15/(1+$B11)^2.5+'04_Valuation'!$F$15/(1+$B11)^3.5+'04_Valuation'!$G$15/(1+$B11)^4.5+('04_Valuation'!$G$15*(1+0.02)/($B11-0.02))/(1+$B11)^4.5)-'01_Assumptions'!$C$30 | E11: =('04_Valuation'!$C$15/(1+$B11)^0.5+'04_Valuation'!$D$15/(1+$B11)^1.5+'04_Valuation'!$E$15/(1+$B11)^2.5+'04_Valuation'!$F$15/(1+$B11)^3.5+'04_Valuation'!$G$15/(1+$B11)^4.5+('04_Valuation'!$G$15*(1+0.025)/($B11-0.025))/(1+$B11)^4.5)-'01_Assumptions'!$C$30 | F11: =('04_Valuation'!$C$15/(1+$B11)^0.5+'04_Valuation'!$D$15/(1+$B11)^1.5+'04_Valuation'!$E$15/(1+$B11)^2.5+'04_Valuation'!$F$15/(1+$B11)^3.5+'04_Valuation'!$G$15/(1+$B11)^4.5+('04_Valuation'!$G$15*(1+0.03)/($B11-0.03))/(1+$B11)^4.5)-'01_Assumptions'!$C$30 | G11: =('04_Valuation'!$C$15/(1+$B11)^0.5+'04_Valuation'!$D$15/(1+$B11)^1.5+'04_Valuation'!$E$15/(1+$B11)^2.5+'04_Valuation'!$F$15/(1+$B11)^3.5+'04_Valuation'!$G$15/(1+$B11)^4.5+('04_Valuation'!$G$15*(1+0.035)/($B11-0.035))/(1+$B11)^4.5)-'01_Assumptions'!$C$30
B12: 0.115 | C12: =('04_Valuation'!$C$15/(1+$B12)^0.5+'04_Valuation'!$D$15/(1+$B12)^1.5+'04_Valuation'!$E$15/(1+$B12)^2.5+'04_Valuation'!$F$15/(1+$B12)^3.5+'04_Valuation'!$G$15/(1+$B12)^4.5+('04_Valuation'!$G$15*(1+0.015)/($B12-0.015))/(1+$B12)^4.5)-'01_Assumptions'!$C$30 | D12: =('04_Valuation'!$C$15/(1+$B12)^0.5+'04_Valuation'!$D$15/(1+$B12)^1.5+'04_Valuation'!$E$15/(1+$B12)^2.5+'04_Valuation'!$F$15/(1+$B12)^3.5+'04_Valuation'!$G$15/(1+$B12)^4.5+('04_Valuation'!$G$15*(1+0.02)/($B12-0.02))/(1+$B12)^4.5)-'01_Assumptions'!$C$30 | E12: =('04_Valuation'!$C$15/(1+$B12)^0.5+'04_Valuation'!$D$15/(1+$B12)^1.5+'04_Valuation'!$E$15/(1+$B12)^2.5+'04_Valuation'!$F$15/(1+$B12)^3.5+'04_Valuation'!$G$15/(1+$B12)^4.5+('04_Valuation'!$G$15*(1+0.025)/($B12-0.025))/(1+$B12)^4.5)-'01_Assumptions'!$C$30 | F12: =('04_Valuation'!$C$15/(1+$B12)^0.5+'04_Valuation'!$D$15/(1+$B12)^1.5+'04_Valuation'!$E$15/(1+$B12)^2.5+'04_Valuation'!$F$15/(1+$B12)^3.5+'04_Valuation'!$G$15/(1+$B12)^4.5+('04_Valuation'!$G$15*(1+0.03)/($B12-0.03))/(1+$B12)^4.5)-'01_Assumptions'!$C$30 | G12: =('04_Valuation'!$C$15/(1+$B12)^0.5+'04_Valuation'!$D$15/(1+$B12)^1.5+'04_Valuation'!$E$15/(1+$B12)^2.5+'04_Valuation'!$F$15/(1+$B12)^3.5+'04_Valuation'!$G$15/(1+$B12)^4.5+('04_Valuation'!$G$15*(1+0.035)/($B12-0.035))/(1+$B12)^4.5)-'01_Assumptions'!$C$30
B14: Base case WACC and g are highlighted conceptually on 03_WACC / 01_Assumptions (≈9.x% WACC, 2.5% g).
B15: Gray cells where g ≥ WACC would be undefined; those combinations are excluded from this grid.

Sheet 06_Data_Dictionary
B2: Data dictionary
B4: Field | C4: Tab | D4: Definition
B5: Revenue | C5: 01_Assumptions | D5: Top-line sales for Northline; Year 0 is LTM, Years 1–5 grow off prior year.
B6: Revenue growth | C6: 01_Assumptions | D6: Year-over-year % applied to build the revenue forecast.
B7: EBITDA margin | C7: 01_Assumptions | D7: EBITDA ÷ Revenue. Path can rise with mix/scale.
B8: D&A % of revenue | C8: 01_Assumptions | D8: Depreciation & amortization as % of revenue.
B9: Capex % of revenue | C9: 01_Assumptions | D9: Cash capital expenditure as % of revenue.
B10: NWC % of revenue | C10: 01_Assumptions | D10: Net working capital balance as % of revenue; ΔNWC is a cash use when the balance rises.
B11: Tax rate | C11: 01_Assumptions | D11: Statutory/ marginal rate applied to EBIT for NOPAT (simplified).
B12: WACC inputs | C12: 01_Assumptions / 03_WACC | D12: CAPM cost of equity and after-tax cost of debt, blended by target capital structure.
B13: Terminal growth g | C13: 01_Assumptions | D13: Perpetuity growth on Year-5 FCF. Must be below WACC.
B14: Net debt | C14: 01_Assumptions | D14: Interest-bearing debt minus cash. Subtracted from EV to get equity value.
B15: Unlevered FCF | C15: 02_FCF_Build | D15: NOPAT + D&A − Capex − ΔNWC. Cash flow to all providers of capital.
... B20: Mid-year convention | C20: 01_Assumptions | D20: If 1, cash flows discounted at mid-year (0.5, 1.5, …). If 0, year-end (1, 2, …).
